odoo/addons/meilisearch_base/LICENSE
odoo/addons/meilisearch_base/README.rst
odoo/addons/meilisearch_base/__init__.py
odoo/addons/meilisearch_base/__manifest__.py
odoo/addons/meilisearch_base/controllers/__init__.py
odoo/addons/meilisearch_base/controllers/main.py
odoo/addons/meilisearch_base/data/cron.xml
odoo/addons/meilisearch_base/demo/meilisearch_index_demo.xml
odoo/addons/meilisearch_base/images/screen.png
odoo/addons/meilisearch_base/models/__init__.py
odoo/addons/meilisearch_base/models/meilisearch_document_mixin.py
odoo/addons/meilisearch_base/models/meilisearch_index.py
odoo/addons/meilisearch_base/models/meilisearch_task.py
odoo/addons/meilisearch_base/models/res_config_settings.py
odoo/addons/meilisearch_base/models/res_country.py
odoo/addons/meilisearch_base/security/ir.model.access.csv
odoo/addons/meilisearch_base/security/security.xml
odoo/addons/meilisearch_base/static/description/icon.png
odoo/addons/meilisearch_base/static/description/icon.svg
odoo/addons/meilisearch_base/static/description/index.html
odoo/addons/meilisearch_base/static/src/css/style.css
odoo/addons/meilisearch_base/tests/TEST_INSTRUCTIONS.rst
odoo/addons/meilisearch_base/tests/__init__.py
odoo/addons/meilisearch_base/tests/test_res_country.py
odoo/addons/meilisearch_base/views/meilisearch_document_views.xml
odoo/addons/meilisearch_base/views/meilisearch_index_views.xml
odoo/addons/meilisearch_base/views/meilisearch_task_views.xml
odoo/addons/meilisearch_base/views/res_config_settings_view.xml
odoo/addons/meilisearch_base/views/res_country_views.xml
odoo_addon_meilisearch_base-18.0.1.0.0.dist-info/METADATA
odoo_addon_meilisearch_base-18.0.1.0.0.dist-info/WHEEL
odoo_addon_meilisearch_base-18.0.1.0.0.dist-info/top_level.txt
odoo_addon_meilisearch_base-18.0.1.0.0.dist-info/RECORD
